notion_pdf_exporter/__init__.py
notion_pdf_exporter/converter.py
notion_pdf_exporter/exporter.py
notion_pdf_exporter/html/__init__.py
notion_pdf_exporter/html/callout.py
notion_pdf_exporter/html/heading.py
notion_pdf_exporter/html/mapping.py
notion_pdf_exporter/html/paragraph.py
notion_pdf_exporter/html/properties.py
notion_pdf_exporter/pdf/__init__.py
notion_pdf_exporter/pdf/converter.py
notion_pdf_exporter/styles/__init__.py
notion_pdf_exporter/styles/default.py
notion_pdf_exporter/styles/style.py
secnex_notion_pdf_exporter-0.0.6.dist-info/METADATA
secnex_notion_pdf_exporter-0.0.6.dist-info/WHEEL
secnex_notion_pdf_exporter-0.0.6.dist-info/entry_points.txt
secnex_notion_pdf_exporter-0.0.6.dist-info/top_level.txt
secnex_notion_pdf_exporter-0.0.6.dist-info/RECORD
